patch_api/__init__.py
patch_api/api_client.py
patch_api/configuration.py
patch_api/exceptions.py
patch_api/rest.py
patch_api/api/__init__.py
patch_api/api/order_line_items_api.py
patch_api/api/orders_api.py
patch_api/api/projects_api.py
patch_api/api/technology_types_api.py
patch_api/models/__init__.py
patch_api/models/create_order_line_item_request.py
patch_api/models/create_order_request.py
patch_api/models/create_success_response.py
patch_api/models/delete_order_response.py
patch_api/models/disclaimer.py
patch_api/models/error_response.py
patch_api/models/highlight.py
patch_api/models/inventory.py
patch_api/models/meta_index_object.py
patch_api/models/order.py
patch_api/models/order_issued_to.py
patch_api/models/order_line_item.py
patch_api/models/order_line_item_project.py
patch_api/models/order_line_item_response.py
patch_api/models/order_list_response.py
patch_api/models/order_response.py
patch_api/models/parent_technology_type.py
patch_api/models/photo.py
patch_api/models/place_order_request.py
patch_api/models/project.py
patch_api/models/project_list_response.py
patch_api/models/project_response.py
patch_api/models/sdg.py
patch_api/models/standard.py
patch_api/models/technology_type.py
patch_api/models/technology_type_list_response.py
patch_api/models/update_order_line_item_request.py
patch_api-2.6.1.dist-info/METADATA
patch_api-2.6.1.dist-info/WHEEL
patch_api-2.6.1.dist-info/top_level.txt
patch_api-2.6.1.dist-info/RECORD
