Metadata-Version: 2.4
Name: patch-api
Version: 2.6.1
Summary: Patch API V2
Home-page: 
Author: Developer Support
Author-email: engineering@usepatch.com
Keywords: OpenAPI,OpenAPI-Generator,Patch API V2
Requires-Python: >=3.6
Requires-Dist: urllib3>=1.25.3
Requires-Dist: python-dateutil
Requires-Dist: certifi
Dynamic: author
Dynamic: author-email
Dynamic: description
Dynamic: keywords
Dynamic: requires-dist
Dynamic: requires-python
Dynamic: summary
